berhoel/odf/__init__.py
"berhoel/odf/__init__.py,cover"
berhoel/odf/ods.py
"berhoel/odf/ods.py,cover"
berhoel/odf/py.typed
berhoel/odf/tests/.ruff.toml
berhoel/odf/tests/.ruff_cache/.gitignore
berhoel/odf/tests/.ruff_cache/0.14.0/13582391407088580440
berhoel/odf/tests/.ruff_cache/0.14.0/14524430045770712246
berhoel/odf/tests/.ruff_cache/0.14.0/6525284336341802665
berhoel/odf/tests/.ruff_cache/0.6.8/17086512131239892168
berhoel/odf/tests/.ruff_cache/CACHEDIR.TAG
berhoel/odf/tests/__init__.py
berhoel/odf/tests/conftest.py
"berhoel/odf/tests/conftest.py,cover"
berhoel/odf/tests/test_odf_base.py
"berhoel/odf/tests/test_odf_base.py,cover"
berhoel/odf/tests/test_ods.py
"berhoel/odf/tests/test_ods.py,cover"
berhoelodf-0.3.0.dist-info/WHEEL
berhoelodf-0.3.0.dist-info/METADATA
berhoelodf-0.3.0.dist-info/RECORD
