Metadata-Version: 2.3
Name: berhoelodf
Version: 0.3.0
Summary: Lightweight and limited access to odf files using lxml.
Author: Berthold Höllmann
Author-email: Berthold Höllmann <berthold-gitlab@xn--hllmanns-n4a.de>
License: MIT
Classifier: Development Status :: 4 - Beta
Classifier: Topic :: Utilities
Requires-Dist: lxml
Maintainer: Berthold Höllmann
Maintainer-email: Berthold Höllmann <berthold-gitlab@xn--hllmanns-n4a.de>
Requires-Python: >=3.13, <4.0
Project-URL: Documentation, https://python.xn--hllmanns-n4a.de/berhoelODF/
Project-URL: Homepage, https://python.xn--hllmanns-n4a.de/berhoelODF/
Project-URL: Repository, https://gitlab.com/berhoel/python/berhoelodf.git
